tex_escape.py
tex_escape-0.1.1.dist-info/METADATA
tex_escape-0.1.1.dist-info/WHEEL
tex_escape-0.1.1.dist-info/entry_points.txt
tex_escape-0.1.1.dist-info/RECORD
