Metadata-Version: 2.1
Name: tex-escape
Version: 0.1.1
Summary: A small package for escaping LaTeX.
Project-URL: Documentation, https://github.com/leonzalion/tex-escape#readme
Project-URL: Issues, https://github.com/leonzalion/tex-escape/issues
Project-URL: Source, https://github.com/leonzalion/tex-escape
Author-email: Leon Si <contact@leonzalion.com>
Classifier: Development Status :: 4 - Beta
Classifier: Programming Language :: Python
Classifier: Programming Language :: Python :: 3.10
Classifier: Programming Language :: Python :: 3.7
Classifier: Programming Language :: Python :: 3.8
Classifier: Programming Language :: Python :: 3.9
Classifier: Programming Language :: Python :: Implementation :: CPython
Classifier: Programming Language :: Python :: Implementation :: PyPy
Requires-Python: >=3.7
